MANIFEST.in
README.md
setup.cfg
setup.py
MessWithDevs/__init__.py
MessWithDevs/commandLine.py
MessWithDevs.egg-info/PKG-INFO
MessWithDevs.egg-info/SOURCES.txt
MessWithDevs.egg-info/dependency_links.txt
MessWithDevs.egg-info/entry_points.txt
MessWithDevs.egg-info/not-zip-safe
MessWithDevs.egg-info/top_level.txt