Metadata-Version: 1.0
Name: MessWithDevs
Version: 0.2
Summary: Swaps characters in a text file with indistinguishable doppelgangers to break code (damage is reversible!)
Home-page: https://github.com/AlexJamesWright/MessWithDevs
Author: Alex James Wright
Author-email: a.j.wright@soton.ac.uk
License: MIT
Keywords: MessWithDevs
Platform: UNKNOWN
